pylgs/__init__.py
pylgs/_modidx.py
pylgs/all.py
pylgs/dmelements.py
pylgs/imports.py
pylgs/lgssystem.py
pylgs/patches.py
pylgs/velocitygroups.py
pylgs/pymor/__init__.py
pylgs/pymor/grids.py
pylgs/pymor/models.py
pylgs/pymor/operators.py
pylgs/pymor/parameters.py
pylgs/pymor/timestepping.py
pylgs/pymor/vectorarrays.py
pylgs/systems/Na330/A_dop.mtxn
pylgs/systems/Na330/A_ind.mtxn
pylgs/systems/Na330/A_rec.mtxn
pylgs/systems/Na330/A_vcc.mtxn
pylgs/systems/Na330/Flux.mtxn
pylgs/systems/Na330/b.mtxn
pylgs/systems/NaD1/A_dop.mtxn
pylgs/systems/NaD1/A_ind.mtxn
pylgs/systems/NaD1/A_rec.mtxn
pylgs/systems/NaD1/A_vcc.mtxn
pylgs/systems/NaD1/Flux.mtxn
pylgs/systems/NaD1/b.mtxn
pylgs/systems/NaD1_Toy/A_dop.mtxn
pylgs/systems/NaD1_Toy/A_ind.mtxn
pylgs/systems/NaD1_Toy/A_rec.mtxn
pylgs/systems/NaD1_Toy/A_vcc.mtxn
pylgs/systems/NaD1_Toy/Flux.mtxn
pylgs/systems/NaD1_Toy/b.mtxn
pylgs/systems/NaD2/A_dop.mtxn
pylgs/systems/NaD2/A_ind.mtxn
pylgs/systems/NaD2/A_rec.mtxn
pylgs/systems/NaD2/A_vcc.mtxn
pylgs/systems/NaD2/Flux.mtxn
pylgs/systems/NaD2/b.mtxn
pylgs/systems/NaD2_Repump/A_dop.mtxn
pylgs/systems/NaD2_Repump/A_ind.mtxn
pylgs/systems/NaD2_Repump/A_rec.mtxn
pylgs/systems/NaD2_Repump/A_vcc.mtxn
pylgs/systems/NaD2_Repump/Flux.mtxn
pylgs/systems/NaD2_Repump/b.mtxn
pylgs/utilities/__init__.py
pylgs/utilities/basic.py
pylgs/utilities/formatting.py
pylgs/utilities/nbdev.py
pylgs/utilities/numpy.py
pylgs/utilities/sparse.py
pylgs/utilities/testing.py
pylgs/utilities/xarray.py
pylgs-0.1.0.dist-info/LICENSE
pylgs-0.1.0.dist-info/METADATA
pylgs-0.1.0.dist-info/WHEEL
pylgs-0.1.0.dist-info/entry_points.txt
pylgs-0.1.0.dist-info/top_level.txt
pylgs-0.1.0.dist-info/RECORD
