Metadata-Version: 2.1
Name: pylgs
Version: 0.1.0
Summary: Modeling atomic physics of laser guide stars
Home-page: https://github.com/simonkeys/pylgs
Author: Simon Rochester
Author-email: simon.rochester@gmail.com
License: GPLv3
Keywords: nbdev jupyter notebook python LGS
Classifier: Development Status :: 4 - Beta
Classifier: Intended Audience :: Developers
Classifier: Natural Language :: English
Classifier: Programming Language :: Python :: 3.10
Requires-Python: >=3.10
License-File: LICENSE
Requires-Dist: fastcore
Requires-Dist: plum-dispatch
Requires-Dist: pydash
Requires-Dist: wrapt
Requires-Dist: pymor
Requires-Dist: scikits.odes
Requires-Dist: sparse
Requires-Dist: sympy
Requires-Dist: xarray
Requires-Dist: opt_einsum
Requires-Dist: einops
Requires-Dist: matplotlib
Requires-Dist: plotly
Requires-Dist: kaleido
Provides-Extra: dev
Requires-Dist: nbdev-simonkeys==2.3.32; extra == "dev"
Requires-Dist: h5netcdf; extra == "dev"
Requires-Dist: jupyter; extra == "dev"
Requires-Dist: jupyterlab-unfold; extra == "dev"
Requires-Dist: jupyterlab-spellchecker; extra == "dev"
